{"set": ["ASTEROID/USDT", "BSB/USDT", "CHIP/USDT", "ENA/USDT", "ESPORTS/USDT", "EVAA/USDT", "JTO/USDT", "PEPE/USDT", "XLM/USDT", "XRP/USDT", "ZRO/USDT"], "left": {"TRADOOR/USDT": 1781535721.159713, "ADA/USDT": 1781542302.2382748, "SIREN/USDT": 1781545307.1217198, "WLFI/USDT": 1781545603.9212775, "CLO/USDT": 1781549220.0672724}, "vals": {"PEPE/USDT": 5.04, "ASTEROID/USDT": 69.97, "CHIP/USDT": 9.87, "EVAA/USDT": 72.78, "ESPORTS/USDT": 5.57, "XRP/USDT": 8.28, "ENA/USDT": 4.6, "ZRO/USDT": 17.33, "XLM/USDT": 14.92, "JTO/USDT": 39.15, "BSB/USDT": 35.48}}