{"set": ["ASTEROID/USDT", "BSB/USDT", "CHIP/USDT", "ENA/USDT", "FARTCOIN/USDT", "JTO/USDT", "LAB/USDT", "SKYAI/USDT", "SPACE/USDT", "UNI/USDT", "VELVET/USDT", "XLM/USDT", "ZRO/USDT"], "left": {"SIREN/USDT": 1781597485.4952133, "WLFI/USDT": 1781597485.4952133}, "vals": {"ASTEROID/USDT": 36.68, "SPACE/USDT": 22.41, "CHIP/USDT": 3.27, "VELVET/USDT": 11.03, "LAB/USDT": 14.14, "SKYAI/USDT": 13.66, "XLM/USDT": 4.61, "ENA/USDT": 3.06, "BSB/USDT": 38.73, "JTO/USDT": 7.56, "ZRO/USDT": 5.39, "FARTCOIN/USDT": 8.62, "UNI/USDT": 6.96}}