{"set": ["ADA/USDT", "AGLD/USDT", "BAS/USDT", "BEAT/USDT", "ESPORTS/USDT", "H/USDT", "LAB/USDT", "MAGMA/USDT", "SKYAI/USDT", "SLX/USDT", "UB/USDT", "VELVET/USDT"], "left": {"BTW/USDT": 1782479795.881762, "PUMP/USDT": 1782482520.7389536, "TNSR/USDT": 1782483095.3601108, "HEI/USDT": 1782483095.3601108}, "vals": {"UB/USDT": 11.35, "BAS/USDT": 8.67, "MAGMA/USDT": 43.8, "VELVET/USDT": 31.06, "AGLD/USDT": 63.82, "LAB/USDT": 5.0, "SLX/USDT": 3.44, "ESPORTS/USDT": 5.82, "BEAT/USDT": 9.49, "ADA/USDT": 3.2, "SKYAI/USDT": 20.12, "H/USDT": 5.41}}